{
  "info": {
    "identifiers": {
      "id": "film_252",
      "actor": "KaDee Strickland"
    }
  },
  "emotions": {
    "arousal": [
      0.75,
      0.75,
      0.75,
      0.75,
      0.75,
      0.75,
      0.75,
      0.75,
      0.75,
      0.75,
      0.75,
      0.75,
      0.75,
      0.75,
      0.75,
      0.75,
      0.75,
      0.75,
      0.75,
      0.75,
      0.75,
      0.75,
      0.75,
      0.75,
      0.75,
      0.75,
      0.75,
      0.75,
      0.75,
      0.75,
      0.75,
      0.75,
      0.75,
      0.75
    ],
    "valence": [
      0.45,
      0.45,
      0.45,
      0.45,
      0.45,
      0.45,
      0.45,
      0.45,
      0.45,
      0.45,
      0.45,
      0.45,
      0.45,
      0.45,
      0.45,
      0.45,
      0.45,
      0.45,
      0.45,
      0.45,
      0.45,
      0.45,
      0.45,
      0.45,
      0.45,
      0.45,
      0.45,
      0.45,
      0.45,
      0.45,
      0.45,
      0.45,
      0.45,
      0.45
    ]
  }
}