{
  "info": {
    "identifiers": {
      "id": "film_318",
      "actor": "Richard Gere"
    }
  },
  "emotions": {
    "arousal": [
      0.6,
      0.6,
      0.6,
      0.6,
      0.6,
      0.6,
      0.6,
      0.6,
      0.65,
      0.65,
      0.65,
      0.65,
      0.65,
      0.65,
      0.65,
      0.65,
      0.65,
      0.65,
      0.65,
      0.65,
      0.65,
      0.65,
      0.65,
      0.65,
      0.65,
      0.65,
      0.65,
      0.65,
      0.65,
      0.65,
      0.65,
      0.65,
      0.65,
      0.65
    ],
    "valence": [
      0.6,
      0.6,
      0.65,
      0.65,
      0.65,
      0.65,
      0.65,
      0.65,
      0.65,
      0.65,
      0.65,
      0.65,
      0.65,
      0.65,
      0.65,
      0.65,
      0.65,
      0.65,
      0.65,
      0.65,
      0.65,
      0.65,
      0.65,
      0.65,
      0.65,
      0.65,
      0.65,
      0.65,
      0.65,
      0.65,
      0.65,
      0.65,
      0.65,
      0.65
    ]
  }
}