{
  "info": {
    "identifiers": {
      "id": "film_486",
      "actor": "Jack Black"
    }
  },
  "emotions": {
    "arousal": [
      0.3,
      0.3,
      0.3,
      0.3,
      0.3,
      0.3,
      0.3,
      0.3,
      0.3,
      0.3,
      0.3,
      0.3,
      0.3,
      0.3,
      0.3,
      0.3,
      0.3,
      0.3,
      0.3,
      0.3,
      0.3,
      0.3,
      0.3,
      0.3,
      0.3,
      0.3,
      0.3,
      0.3,
      0.3,
      0.3,
      0.3,
      0.25,
      0.25,
      0.25
    ],
    "valence": [
      0.2,
      0.2,
      0.2,
      0.2,
      0.2,
      0.2,
      0.2,
      0.2,
      0.25,
      0.25,
      0.25,
      0.25,
      0.25,
      0.25,
      0.25,
      0.25,
      0.25,
      0.25,
      0.25,
      0.25,
      0.25,
      0.25,
      0.25,
      0.25,
      0.25,
      0.25,
      0.25,
      0.25,
      0.25,
      0.25,
      0.25,
      0.25,
      0.25,
      0.25
    ]
  }
}